merakitoolkit/__init__.py
merakitoolkit/__main__.py
merakitoolkit/merakitoolkit.py
merakitoolkit/merakitoolkitparser.py
merakitoolkit/merakitoolkitsupport.py
merakitoolkit/templates/psk/default/__init__.py
merakitoolkit/templates/psk/default/logo.png
merakitoolkit/templates/psk/default/templatehtml.j2
merakitoolkit/templates/psk/default/templatetxt.j2
merakitoolkit-1.1.5.dist-info/LICENSE
merakitoolkit-1.1.5.dist-info/METADATA
merakitoolkit-1.1.5.dist-info/WHEEL
merakitoolkit-1.1.5.dist-info/entry_points.txt
merakitoolkit-1.1.5.dist-info/top_level.txt
merakitoolkit-1.1.5.dist-info/RECORD
