Metadata-Version: 2.1
Name: merakitoolkit
Version: 1.1.5
Summary: merakitoolkit is a Python application to automate specific tasks with Meraki Cloud networks.
Author-email: Giovanni Augusto <author@example.com>
License: MIT License        
Project-URL: Homepage, https://github.com/g1augusto/merakitoolkit
Keywords: meraki,wireless
Classifier: Programming Language :: Python :: 3
Classifier: License :: OSI Approved :: MIT License
Classifier: Operating System :: OS Independent
Classifier: Topic :: System :: Networking
Requires-Python: >=3.8
License-File: LICENSE
Requires-Dist: jinja2 (>=3.1.2)
Requires-Dist: meraki (>=1.24.0)
Requires-Dist: pypng (>=0.20220715.0)
Requires-Dist: pyqrcode (>=1.2.1)
Requires-Dist: xkcdpass (>=1.19.3)
Provides-Extra: dev
Requires-Dist: pylint (>=2.15.0) ; extra == 'dev'
Requires-Dist: pytest (>=7.1.2) ; extra == 'dev'
Requires-Dist: third-party-license-file-generator (>=2022.3.1) ; extra == 'dev'
